<?xml version="1.0" ?>
<routes>
  <route id="959" town="Town12">
    <weathers>
      <weather route_percentage="0" cloudiness="20.0" precipitation="30.0" precipitation_deposits="50.0" wetness="0.0" wind_intensity="30.0" sun_azimuth_angle="-1.0" sun_altitude_angle="45.0" fog_density="3.0"/>
      <weather route_percentage="100" cloudiness="60.0" precipitation="60.0" precipitation_deposits="60.0" wetness="0.0" wind_intensity="60.0" sun_azimuth_angle="-1.0" sun_altitude_angle="45.0" fog_density="3.0"/>
    </weathers>
    <waypoints>
      <position x="986.9" y="5191.2" z="371.6" yaw="270.1"/>
      <position x="852.8" y="4991.3" z="371.3" yaw="178.3"/>
    </waypoints>
    <scenarios>
      <scenario name="VehicleOpensDoorTwoWays_12" type="VehicleOpensDoorTwoWays">
        <trigger_point x="986.9" y="5191.2" z="371.6" yaw="270.1"/>
        <frequency from="35" to="80"/>
        <distance value="67"/>
      </scenario>
    </scenarios>
  </route>
  <route id="3959" town="Town12">
    <weathers>
      <weather route_percentage="0" cloudiness="40.0" precipitation="100.0" precipitation_deposits="90.0" wetness="0.0" wind_intensity="100.0" sun_azimuth_angle="-1.0" sun_altitude_angle="0.0" fog_density="7.0"/>
      <weather route_percentage="100" cloudiness="100.0" precipitation="60.0" precipitation_deposits="60.0" wetness="0.0" wind_intensity="60.0" sun_azimuth_angle="-1.0" sun_altitude_angle="45.0" fog_density="50.0"/>
    </weathers>
    <waypoints>
      <position x="986.9" y="5191.2" z="371.6" yaw="270.1"/>
      <position x="852.8" y="4991.3" z="371.3" yaw="178.3"/>
    </waypoints>
    <scenarios>
      <scenario name="VehicleOpensDoorTwoWays_12" type="VehicleOpensDoorTwoWays">
        <trigger_point x="986.9" y="5191.2" z="371.6" yaw="270.1"/>
        <frequency from="35" to="80"/>
        <distance value="67"/>
      </scenario>
    </scenarios>
  </route>
  <route id="6959" town="Town12">
    <weathers>
      <weather route_percentage="0" cloudiness="60.0" precipitation="30.0" precipitation_deposits="50.0" wetness="60.0" wind_intensity="30.0" sun_azimuth_angle="-1.0" sun_altitude_angle="-90.0" fog_density="3.0"/>
      <weather route_percentage="100" cloudiness="100.0" precipitation="100.0" precipitation_deposits="90.0" wetness="100.0" wind_intensity="100.0" sun_azimuth_angle="-1.0" sun_altitude_angle="-90.0" fog_density="3.0"/>
    </weathers>
    <waypoints>
      <position x="986.9" y="5191.2" z="371.6" yaw="270.1"/>
      <position x="852.8" y="4991.3" z="371.3" yaw="178.3"/>
    </waypoints>
    <scenarios>
      <scenario name="VehicleOpensDoorTwoWays_12" type="VehicleOpensDoorTwoWays">
        <trigger_point x="986.9" y="5191.2" z="371.6" yaw="270.1"/>
        <frequency from="35" to="80"/>
        <distance value="67"/>
      </scenario>
    </scenarios>
  </route>
</routes>
